target_s3_json/__init__.py
target_s3_json/logging.conf
target_s3_json/s3.py
target_s3_jsonl-2.0.1.dist-info/LICENSE
target_s3_jsonl-2.0.1.dist-info/METADATA
target_s3_jsonl-2.0.1.dist-info/WHEEL
target_s3_jsonl-2.0.1.dist-info/entry_points.txt
target_s3_jsonl-2.0.1.dist-info/top_level.txt
target_s3_jsonl-2.0.1.dist-info/RECORD
