Metadata-Version: 2.1
Name: target-s3-jsonl
Version: 2.0.1
Summary: Singer.io target for writing JSON Line files and upload to S3
Home-page: https://github.com/ome9ax/target-s3-jsonl
Author: Eddy ∆
Author-email: edrdelta@gmail.com
License: Apache License 2.0
Project-URL: Releases, https://github.com/ome9ax/target-s3-jsonl/releases
Project-URL: Changelog, https://github.com/ome9ax/target-s3-jsonl/blob/main/CHANGELOG.md
Project-URL: Issue Tracker, https://github.com/ome9ax/target-s3-jsonl/issues
Keywords: target-core,target-s3-jsonl,target-s3-json,singer,singer.io,tap,target,etl,json,jsonl,aws,s3
Classifier: Development Status :: 5 - Production/Stable
Classifier: Operating System :: OS Independent
Classifier: License :: OSI Approved :: Apache Software License
Classifier: Programming Language :: Python :: 3
Classifier: Programming Language :: Python :: 3.9
Classifier: Programming Language :: Python :: 3.10
Requires-Python: >=3.9
License-File: LICENSE
Requires-Dist: target-core (==0.0.7)
Requires-Dist: boto3 (==1.24.91)
Provides-Extra: deploy
Requires-Dist: twine ; extra == 'deploy'
Provides-Extra: dist
Requires-Dist: setuptools ; extra == 'dist'
Requires-Dist: wheel ; extra == 'dist'
Requires-Dist: build ; extra == 'dist'
Provides-Extra: doc
Requires-Dist: sphinx-rtd-theme ; extra == 'doc'
Provides-Extra: lint
Requires-Dist: flake8 ; extra == 'lint'
Provides-Extra: static
Requires-Dist: mypy ; extra == 'static'
Provides-Extra: test
Requires-Dist: pytest-asyncio ; extra == 'test'
Requires-Dist: pytest-cov ; extra == 'test'
Requires-Dist: moto[s3] ; extra == 'test'
